misaki_ja_lightning/__init__.py
misaki_ja_lightning/cutlet.py
misaki_ja_lightning/ja.py
misaki_ja_lightning/num2kana.py
misaki_ja_lightning/token.py
misaki_ja_lightning/unidic_downloader.py
misaki_ja_lightning/data/__init__.py
misaki_ja_lightning/data/ja_words.txt
misaki_ja_lightning-2.0.3.dist-info/licenses/LICENSE
misaki_ja_lightning-2.0.3.dist-info/METADATA
misaki_ja_lightning-2.0.3.dist-info/WHEEL
misaki_ja_lightning-2.0.3.dist-info/top_level.txt
misaki_ja_lightning-2.0.3.dist-info/RECORD
