Metadata-Version: 2.4
Name: misaki-ja-lightning
Version: 2.0.3
Summary: Lightweight Japanese text-to-IPA phoneme converter extracted from misaki
Home-page: https://github.com/yourusername/misaki-ja-lightning
Author: Your Name
Author-email: Your Name <your.email@example.com>
License: MIT
Project-URL: Homepage, https://github.com/yourusername/misaki-ja-lightning
Project-URL: Repository, https://github.com/yourusername/misaki-ja-lightning
Project-URL: Bug Tracker, https://github.com/yourusername/misaki-ja-lightning/issues
Keywords: japanese,nlp,tts,phoneme,ipa,g2p,text-to-speech
Classifier: Development Status :: 3 - Alpha
Classifier: Intended Audience :: Developers
Classifier: Topic :: Text Processing :: Linguistic
Classifier: License :: OSI Approved :: MIT License
Classifier: Programming Language :: Python :: 3
Classifier: Programming Language :: Python :: 3.8
Classifier: Programming Language :: Python :: 3.9
Classifier: Programming Language :: Python :: 3.10
Classifier: Programming Language :: Python :: 3.11
Requires-Python: >=3.8
License-File: LICENSE
Requires-Dist: fugashi==1.4.0
Requires-Dist: mecab-python3
Requires-Dist: jaconv==0.4.0
Requires-Dist: mojimoji==0.0.13
Requires-Dist: pyopenjtalk-somniumism>=0.1.dev0
Provides-Extra: unidic
Requires-Dist: unidic-lite; extra == "unidic"
Dynamic: author
Dynamic: home-page
Dynamic: license-file
Dynamic: requires-python
